test/__init__.py
test/interpreter/__init__.py
test/interpreter/test_lexer.py
test/interpreter/test_parser.py
test/interpreter/test_source.py
test/truck/__init__.py
test/truck/test_class.py
test/truck/test_function.py
truck/__init__.py
truck/__main__.py
truck/truck.py
truck/interpreter/__init__.py
truck/interpreter/environ.py
truck/interpreter/lexer.py
truck/interpreter/optimizer.py
truck/interpreter/parser.py
truck/interpreter/source.py
truck/interpreter/ast/__init__.py
truck/interpreter/ast/assign.py
truck/interpreter/ast/block.py
truck/interpreter/ast/break_.py
truck/interpreter/ast/class_.py
truck/interpreter/ast/continue_.py
truck/interpreter/ast/expr.py
truck/interpreter/ast/function.py
truck/interpreter/ast/ident.py
truck/interpreter/ast/if_.py
truck/interpreter/ast/new.py
truck/interpreter/ast/params.py
truck/interpreter/ast/program.py
truck/interpreter/ast/return_.py
truck/interpreter/ast/use.py
truck/interpreter/ast/while_.py
truck/lib/__init__.py
truck/lib/io.truck
truck/lib/math.truck
trucklang-0.1.1.dist-info/LICENSE
trucklang-0.1.1.dist-info/METADATA
trucklang-0.1.1.dist-info/WHEEL
trucklang-0.1.1.dist-info/top_level.txt
trucklang-0.1.1.dist-info/RECORD
