Metadata-Version: 2.1
Name: trucklang
Version: 0.1.1
Summary: A dynamic object oriented programming language with a focus on simplicity
Home-page: http://github.com/tarptaeya/truck
Author: Anmol Gautam
Author-email: tarptaeya@gmail.com
License: UNKNOWN
Platform: UNKNOWN
Classifier: Programming Language :: Python :: 3
Classifier: License :: OSI Approved :: MIT License
Classifier: Operating System :: OS Independent
Requires-Python: >=3.5
